Workbook
Name Slicer_Channel: #N/A
Name Slicer_Region: #N/A

Sheet Campaign_Data_Q3
A1: Campaign_ID | B1: Campaign_Name | C1: Channel | D1: Start_Date | E1: End_Date | F1: Ad_Spend (NGN) | G1: Impressions | H1: Clicks | I1: Leads | J1: Conversions | K1: Revenue (NGN) | L1: ROI (%) | M1: Region | N1: Campaign_Status | O1: Account_Manager
A2: C001 | B2: Summer Email Blast | C2: Email | D2: 45474 | E2: 45504 | F2: 450000 | G2: 120000 | H2: 3600 | I2: 180 | J2: 45 | K2: 1800000 | L2: 300 | M2: Lagos | N2: Completed | O2: Amaka Obi
A3: C002 | B3: Google Ads - Promo | C3: Paid Ads | D3: 45478 | E3: 45503 | F3: 820000 | G3: 350000 | H3: 7000 | I3: 210 | J3: 63 | K3: 2460000 | L3: 200 | M3: Abuja | N3: Completed | O3: Tunde Adeyemi
A4: C003 | B4: Instagram Summer | C4: Social Media | D4: 45474 | E4: 45504 | F4: 300000 | G4: 95000 | H4: 2850 | I4: 95 | J4: 28 | K4: 560000 | L4: 87 | M4: Lagos | N4: Completed | O4: Amaka Obi
A5: C004 | B5: LinkedIn B2B Push | C5: Social Media | D5: 45483 | G5: 210000 | H5: 6300 | I5: 315 | J5: 72 | K5: 2880000 | N5: Abuja | O5: Running | P5: Chidi Nwosu
A6: C005 | B6: Email Newsletter July | C6: Email | D6: 45488 | E6: 45504 | F6: 195000 | G6: 88000 | H6: 2640 | I6: 132 | J6: 33 | K6: 990000 | L6: 408 | M6: Port Harcourt | N6: Completed | O6: Sola Fashola
A7: C006 | B7: Facebook Retargeting | C7: Paid Ads | D7: 45493 | E7: 45504 | F7: 620000 | G7: 430000 | H7: 8600 | I7: 258 | J7: 51 | K7: 1530000 | L7: 147 | M7: Lagos | N7: Completed | O7: Tunde Adeyemi
A8: C007 | B8: YouTube Pre-roll | C8: Video Ads | D8: 45495 | E8: 45514 | F8: 510000 | G8: 780000 | H8: 11700 | I8: 351 | J8: 70 | K8: 2100000 | L8: 312 | M8: Nationwide | N8: Completed | O8: Chidi Nwosu
A9: C008 | B9: Affiliate Campaign Q3 | C9: Affiliate | D9: 45505 | E9: 45535 | F9: 380000 | G9: 165000 | H9: 4950 | I9: 247 | J9: 61 | K9: 1830000 | L9: 382 | M9: Lagos | N9: completed | O9: Amaka Obi
A10: C009 | B10: Google Search - Aug | C10: Paid Ads | D10: 45505 | E10: 45535 | F10: 910000 | G10: 480000 | H10: 9600 | I10: 384 | J10: 96 | K10: 3840000 | L10: 322 | M10: Abuja | N10: Completed | O10: Tunde Adeyemi
A11: C010 | B11: Email - August Promo | C11: Email | D11: 45509 | E11: 45529 | F11: 210000 | G11: 102000 | H11: 3060 | I11: 153 | J11: 38 | K11: 1140000 | L11: 443 | M11: Port Harcourt | N11: Completed | O11: Sola Fashola
A12: C011 | B12: Social - August Deals | C12: Social Media | D12: 45514 | E12: 45535 | F12: 270000 | G12: 113000 | H12: 3390 | I12: 169 | J12: 42 | K12: 1260000 | L12: 367 | M12: Lagos | N12: Completed
A13: C012 | B13: TikTok Brand Awareness | C13: Video Ads | D13: 45516 | E13: 45535 | F13: 430000 | G13: 920000 | H13: 18400 | I13: 552 | J13: 83 | K13: 2490000 | L13: 479 | M13: Nationwide | N13: Completed | O13: Chidi Nwosu
A14: C013 | B14: Influencer Collab Aug | C14: Influencer | D14: 45518 | E14: 45532 | F14: 600000 | G14: 540000 | H14: 16200 | I14: 486 | J14: 97 | K14: 3880000 | L14: 547 | M14: Lagos | N14: Completed | O14: Amaka Obi
A15: C014 | B15: LinkedIn Lead Gen | C15: Social Media | D15: 45522 | E15: 45535 | F15: 340000 | G15: 78000 | H15: 2340 | I15: 117 | J15: 29 | K15: 1160000 | L15: 241 | M15: Abuja | N15: Completed | O15: Chidi Nwosu
A16: C015 | B16: Email Blast - Sept | C16: Email | D16: 45536 | E16: 45565 | F16: 225000 | G16: 111000 | H16: 3330 | I16: 166 | J16: 41 | K16: 1230000 | L16: 447 | M16: Port Harcourt | N16: Completed | O16: Sola Fashola
A17: C016 | B17: Google Ads - Sept | C17: Paid Ads | D17: 45536 | E17: 45565 | F17: 980000 | G17: 510000 | H17: 10200 | I17: 408 | J17: 102 | K17: 4080000 | L17: 316 | M17: Abuja | N17: Completed | O17: Tunde Adeyemi
A18: C017 | B18: Instagram Autumn | C18: Social Media | D18: 45540 | E18: 45565 | F18: 310000 | G18: 102000 | H18: 3060 | I18: 153 | J18: 38 | K18: 1520000 | L18: 390 | M18: Lagos | N18: Completed | O18: Amaka Obi
A19: C018 | B19: Facebook Sept Promo | C19: Paid Ads | D19: 45545 | E19: 45565 | F19: 530000 | G19: 360000 | H19: 7200 | I19: 216 | J19: 54 | K19: 2160000 | L19: 308 | M19: Lagos | N19: Completed | O19: Tunde Adeyemi
A20: C019 | B20: Podcast Sponsorship | C20: Audio Ads | D20: 45547 | E20: 45565 | F20: 400000 | G20: 200000 | H20: 4000 | I20: 120 | J20: 24 | K20: 960000 | L20: 140 | M20: Nationwide | N20: Completed | O20: Sola Fashola
A21: C020 | B21: End-of-Quarter Blast | C21: Email | D21: 45560 | E21: 45565 | F21: 180000 | G21: 95000 | H21: 2850 | I21: 142 | J21: 36 | K21: 1440000 | L21: 700 | M21: Lagos | N21: Completed | O21: Amaka Obi
A22: C001 | B22: Summer Email Blast | C22: Email | D22: 45474 | E22: 45504 | F22: 450000 | G22: 120000 | H22: 3600 | I22: 180 | J22: 45 | K22: 1800000 | L22: 300 | M22: Lagos | N22: Completed | O22: Amaka Obi
A23: C003 | B23: Instagram Summer | C23: Social Media | D23: 45474 | E23: 45504 | F23: 300000 | G23: 95000 | H23: 2850 | I23: 95 | J23: 28 | K23: 560000 | L23: 87 | M23: Lagos | N23: Completed | O23: Amaka Obi
A24: C021 | B24: Display Ads - Q3 | C24: Display | D24: 45481 | E24: 45565 | F24: 750000 | G24: 1200000 | H24: 24000 | I24: 720 | J24: 144 | K24: 5760000 | L24: 668 | M24: Nationwide | N24: Completed | O24: Chidi Nwosu
A25: C022 | B25: WhatsApp Campaign | C25: Messaging | D25: 45524 | E25: 45535 | F25: N/A | G25: 50000 | H25: 1500 | I25: 75 | J25: 18 | K25: 720000 | M25: Lagos | N25: Completed | O25: Amaka Obi
A26: C023 | B26: Radio Digital Ad | C26: Audio Ads | D26: 45536 | E26: 45550 | F26: 280000 | G26: 90000 | H26: 1800 | I26: 54 | J26: 11 | K26: 440000 | L26: 57 | M26: Port Harcourt | N26: Completed | O26: Sola Fashola
A27: C024 | B27: SEO Content Push | C27: Organic | D27: 45474 | E27: 45565 | F27: 0 | G27: 320000 | H27: 9600 | I27: 480 | J27: 120 | K27: 4800000 | M27: Nationwide | N27: Completed | O27: Chidi Nwosu
A28: C025 | B28: Twitter/X Campaign | C28: Social Media | D28: 45505 | E28: 45535 | F28: 190000 | G28: 145000 | H28: 4350 | I28: 217 | J28: 43 | K28: 1720000 | L28: 805 | M28: Lagos | N28: Completed | O28: Amaka Obi
A29: C026 | B29: Email Segmented - VIP | C29: Email | D29: 45553 | E29: 45565 | F29: 85000 | G29: 22000 | H29: 660 | I29: 99 | J29: 33 | K29: 1980000 | M29: Abuja | N29: Completed | O29: Tunde Adeyemi
A30: C027 | B30: Programmatic Ads | C30: Paid Ads | D30: 45488 | E30: 45519 | F30: 670000 | G30: 890000 | H30: 17800 | I30: 534 | J30: 89 | K30: 3560000 | L30: 431 | M30: Nationwide | N30: completed | O30: Chidi Nwosu
A31: C028 | B31: Google Display Net | C31: Display | D31: 45540 | E31: 45565 | F31: 490000 | G31: 620000 | H31: 12400 | I31: 310 | J31: 62 | K31: 2480000 | L31: 406 | M31: Abuja | N31: Completed | O31: Tunde Adeyemi
A32: C029 | B32: End of Q3 Social | C32: Social Media | D32: 45563 | E32: 45565 | F32: 120000 | G32: 40000 | H32: 1200 | I32: 60 | J32: 12 | K32: - | M32: Lagos | N32: Pending
A33: C030 | B33: Referral Programme | C33: Referral | D33: 45474 | E33: 45565 | F33: 250000 | H33: 3000 | I33: 600 | J33: 200 | K33: 8000000 | L33: 3100 | M33: Nationwide | N33: Completed | O33: Amaka Obi

Sheet Cleaned Data
A1: Campaign_ID | B1: Campaign_Name | C1: Channel | D1: Start_Date | E1: End_Date | F1: Ad_Spend (NGN) | G1: Impressions | H1: Clicks | I1: Leads | J1: Conversions | K1: Revenue (NGN) | L1: ROI (%) | M1: Region | N1: Campaign_Status | O1: Account_Manager | P1: Conversion Rate (%) | Q1: Cost Per Lead | R1: Click-Through-Rate | S1: Month | T1: Segment
A2: C001 | B2: Summer Email Blast | C2: Email | D2: 45474 | E2: 45504 | F2: 450000 | G2: 120000 | H2: 3600 | I2: 180 | J2: 45 | K2: 1800000 | L2: 300 | M2: Lagos | N2: Completed | O2: Amaka Obi | P2: =(J2/I2)*100 -> 25 | Q2: =(F2/I2) -> 2500 | R2: =IF(G2=0,0,(H2/G2)*100) -> 3 | S2: =TEXT(D2, "mmmm") -> July | T2: =IF(L2>=300,"High Performer",IF(L2>=100,"Average Performer","Low Performer")) -> High Performer
A3: C002 | B3: Google Ads 0 Promo | C3: Paid Ads | D3: 45478 | E3: 45503 | F3: 820000 | G3: 350000 | H3: 7000 | I3: 210 | J3: 63 | K3: 2460000 | L3: 200 | M3: Abuja | N3: Completed | O3: Tunde Adeyemi | P3: =(J3/I3)*100 -> 30 | Q3: =(F3/I3) -> 3904.7619 | R3: =IF(G3=0,0,(H3/G3)*100) -> 2 | S3: =TEXT(D3, "mmmm") -> July | T3: =IF(L3>=300,"High Performer",IF(L3>=100,"Average Performer","Low Performer")) -> Average Performer
A4: C003 | B4: Instagram Summer | C4: Social Media | D4: 45474 | E4: 45504 | F4: 300000 | G4: 95000 | H4: 2850 | I4: 95 | J4: 28 | K4: 560000 | L4: 87 | M4: Lagos | N4: Completed | O4: Amaka Obi | P4: =(J4/I4)*100 -> 29.473684 | Q4: =(F4/I4) -> 3157.8947 | R4: =IF(G4=0,0,(H4/G4)*100) -> 3 | S4: =TEXT(D4, "mmmm") -> July | T4: =IF(L4>=300,"High Performer",IF(L4>=100,"Average Performer","Low Performer")) -> Low Performer
A5: C004 | B5: LinkedIn B2B Push | C5: Social Media | D5: 45483 | F5: 0 | G5: 210000 | H5: 6300 | I5: 315 | J5: 72 | K5: 2880000 | L5: 0 | M5: Abuja | N5: Completed | O5: Chidi Nwosu | P5: =(J5/I5)*100 -> 22.857143 | Q5: =(F5/I5) -> 0 | R5: =IF(G5=0,0,(H5/G5)*100) -> 3 | S5: =TEXT(D5, "mmmm") -> July | T5: =IF(L5>=300,"High Performer",IF(L5>=100,"Average Performer","Low Performer")) -> Low Performer
A6: C005 | B6: Email Newsletter July | C6: Email | D6: 45488 | E6: 45504 | F6: 195000 | G6: 88000 | H6: 2640 | I6: 132 | J6: 33 | K6: 990000 | L6: 408 | M6: Port Harcourt | N6: Completed | O6: Sola Fashola | P6: =(J6/I6)*100 -> 25 | Q6: =(F6/I6) -> 1477.2727 | R6: =IF(G6=0,0,(H6/G6)*100) -> 3 | S6: =TEXT(D6, "mmmm") -> July | T6: =IF(L6>=300,"High Performer",IF(L6>=100,"Average Performer","Low Performer")) -> High Performer
A7: C006 | B7: Facebook Retargeting | C7: Paid Ads | D7: 45493 | E7: 45504 | F7: 620000 | G7: 430000 | H7: 8600 | I7: 258 | J7: 33 | K7: 1530000 | L7: 147 | M7: Lagos | N7: Completed | O7: Tunde Adeyemi | P7: =(J7/I7)*100 -> 12.790698 | Q7: =(F7/I7) -> 2403.1008 | R7: =IF(G7=0,0,(H7/G7)*100) -> 2 | S7: =TEXT(D7, "mmmm") -> July | T7: =IF(L7>=300,"High Performer",IF(L7>=100,"Average Performer","Low Performer")) -> Average Performer
A8: C007 | B8: YouTube Pre0roll | C8: Video Ads | D8: 45495 | E8: 45514 | F8: 510000 | G8: 780000 | H8: 11700 | I8: 351 | J8: 70 | K8: 2100000 | L8: 312 | M8: Nationwide | N8: Completed | O8: Chidi Nwosu | P8: =(J8/I8)*100 -> 19.94302 | Q8: =(F8/I8) -> 1452.9915 | R8: =IF(G8=0,0,(H8/G8)*100) -> 1.5 | S8: =TEXT(D8, "mmmm") -> July | T8: =IF(L8>=300,"High Performer",IF(L8>=100,"Average Performer","Low Performer")) -> High Performer
A9: C008 | B9: Affiliate Campaign Q3 | C9: Affiliate | D9: 45505 | E9: 45535 | F9: 380000 | G9: 165000 | H9: 4950 | I9: 247 | J9: 61 | K9: 1830000 | L9: 382 | M9: Lagos | N9: Completed | O9: Amaka Obi | P9: =(J9/I9)*100 -> 24.696356 | Q9: =(F9/I9) -> 1538.4615 | R9: =IF(G9=0,0,(H9/G9)*100) -> 3 | S9: =TEXT(D9, "mmmm") -> August | T9: =IF(L9>=300,"High Performer",IF(L9>=100,"Average Performer","Low Performer")) -> High Performer
A10: C009 | B10: Google Search 0 Aug | C10: Paid Ads | D10: 45505 | E10: 45535 | F10: 910000 | G10: 480000 | H10: 9600 | I10: 384 | J10: 96 | K10: 3840000 | L10: 322 | M10: Abuja | N10: Completed | O10: Tunde Adeyemi | P10: =(J10/I10)*100 -> 25 | Q10: =(F10/I10) -> 2369.7917 | R10: =IF(G10=0,0,(H10/G10)*100) -> 2 | S10: =TEXT(D10, "mmmm") -> August | T10: =IF(L10>=300,"High Performer",IF(L10>=100,"Average Performer","Low Performer")) -> High Performer
A11: C010 | B11: Email 0 August Promo | C11: Email | D11: 45509 | E11: 45529 | F11: 210000 | G11: 102000 | H11: 3060 | I11: 153 | J11: 38 | K11: 1140000 | L11: 443 | M11: Port Harcourt | N11: Completed | O11: Sola Fashola | P11: =(J11/I11)*100 -> 24.836601 | Q11: =(F11/I11) -> 1372.549 | R11: =IF(G11=0,0,(H11/G11)*100) -> 3 | S11: =TEXT(D11, "mmmm") -> August | T11: =IF(L11>=300,"High Performer",IF(L11>=100,"Average Performer","Low Performer")) -> High Performer
A12: C011 | B12: Social 0 August Deals | C12: Social Media | D12: 45514 | E12: 45535 | F12: 270000 | G12: 113000 | H12: 3390 | I12: 169 | J12: 42 | K12: 1260000 | L12: 367 | M12: Lagos | N12: Completed | O12: Unknown-Pending Confirmation | P12: =(J12/I12)*100 -> 24.852071 | Q12: =(F12/I12) -> 1597.6331 | R12: =IF(G12=0,0,(H12/G12)*100) -> 3 | S12: =TEXT(D12, "mmmm") -> August | T12: =IF(L12>=300,"High Performer",IF(L12>=100,"Average Performer","Low Performer")) -> High Performer
A13: C012 | B13: TikTok Brand Awareness | C13: Video Ads | D13: 45516 | E13: 45535 | F13: 430000 | G13: 920000 | H13: 18400 | I13: 552 | J13: 83 | K13: 2490000 | L13: 479 | M13: Nationwide | N13: Completed | O13: Chidi Nwosu | P13: =(J13/I13)*100 -> 15.036232 | Q13: =(F13/I13) -> 778.98551 | R13: =IF(G13=0,0,(H13/G13)*100) -> 2 | S13: =TEXT(D13, "mmmm") -> August | T13: =IF(L13>=300,"High Performer",IF(L13>=100,"Average Performer","Low Performer")) -> High Performer
A14: C013 | B14: Influencer Collab Aug | C14: Influencer | D14: 45518 | E14: 45532 | F14: 600000 | G14: 540000 | H14: 16200 | I14: 486 | J14: 97 | K14: 3880000 | L14: 547 | M14: Lagos | N14: Completed | O14: Amaka Obi | P14: =(J14/I14)*100 -> 19.958848 | Q14: =(F14/I14) -> 1234.5679 | R14: =IF(G14=0,0,(H14/G14)*100) -> 3 | S14: =TEXT(D14, "mmmm") -> August | T14: =IF(L14>=300,"High Performer",IF(L14>=100,"Average Performer","Low Performer")) -> High Performer
A15: C014 | B15: LinkedIn Lead Gen | C15: Social Media | D15: 45522 | E15: 45535 | F15: 340000 | G15: 78000 | H15: 2340 | I15: 117 | J15: 29 | K15: 1160000 | L15: 241 | M15: Abuja | N15: Completed | O15: Chidi Nwosu | P15: =(J15/I15)*100 -> 24.786325 | Q15: =(F15/I15) -> 2905.9829 | R15: =IF(G15=0,0,(H15/G15)*100) -> 3 | S15: =TEXT(D15, "mmmm") -> August | T15: =IF(L15>=300,"High Performer",IF(L15>=100,"Average Performer","Low Performer")) -> Average Performer
A16: C015 | B16: Email Blast 0 Sept | C16: Email | D16: 45536 | E16: 45565 | F16: 225000 | G16: 111000 | H16: 3330 | I16: 166 | J16: 41 | K16: 1230000 | L16: 447 | M16: Port Harcourt | N16: Completed | O16: Sola Fashola | P16: =(J16/I16)*100 -> 24.698795 | Q16: =(F16/I16) -> 1355.4217 | R16: =IF(G16=0,0,(H16/G16)*100) -> 3 | S16: =TEXT(D16, "mmmm") -> September | T16: =IF(L16>=300,"High Performer",IF(L16>=100,"Average Performer","Low Performer")) -> High Performer
A17: C016 | B17: Google Ads 0 Sept | C17: Paid Ads | D17: 45536 | E17: 45565 | F17: 980000 | G17: 510000 | H17: 10200 | I17: 408 | J17: 102 | K17: 4080000 | L17: 316 | M17: Abuja | N17: Completed | O17: Tunde Adeyemi | P17: =(J17/I17)*100 -> 25 | Q17: =(F17/I17) -> 2401.9608 | R17: =IF(G17=0,0,(H17/G17)*100) -> 2 | S17: =TEXT(D17, "mmmm") -> September | T17: =IF(L17>=300,"High Performer",IF(L17>=100,"Average Performer","Low Performer")) -> High Performer
... A31: C030 | B31: Referral Programme | C31: Referral | D31: 45474 | E31: 45565 | F31: 250000 | G31: 0 | H31: 3000 | I31: 600 | J31: 200 | K31: 8000000 | L31: 3100 | M31: Nationwide | N31: Completed | O31: Amaka Obi | P31: =(J31/I31)*100 -> 33.333333 | Q31: =(F31/I31) -> 416.66667 | R31: =IF(G31=0,0,(H31/G31)*100) -> 0 | S31: =TEXT(D31, "mmmm") -> July | T31: =IF(L31>=300,"High Performer",IF(L31>=100,"Average Performer","Low Performer")) -> High Performer
F32: =SUM(F2:F21) -> 8660000 | K32: =SUM(K2:K31) -> 68770000 | L32: =((K2-H2)/H2)*100 -> 49900

Sheet Summary Statistics
A1: Total Ad Spend | D1: Total Leads Generated
A2: =SUM('Cleaned Data'!F2:F31) -> 11495000 | D2: =SUM('Cleaned Data'!I2:I31) -> 8003
A4: Total Revenue | D4: Total Conversions
A5: =SUM('Cleaned Data'!K2:K31) -> 68770000 | D5: =SUM('Cleaned Data'!J2:J31) -> 1817
A7: Average ROI % | D7: Overall Conversion Rate
A8: =AVERAGE('Cleaned Data'!L2:L31) -> 400.1 | D8: =SUM('Cleaned Data'!J2:J31)/SUM('Cleaned Data'!I2:I31)*100 -> 22.703986
A10: Highest ROI%
A11: =MAX('Cleaned Data'!L2:L29) -> 805 | D11: Channel | E11: Total Revenue
D12: Email | E12: =SUMIF('Cleaned Data'!C:C,"Email",'Cleaned Data'!K:K) -> 8580000
A13: Lowest ROI% | D13: PaidAds | E13: =SUMIF('Cleaned Data'!C:C,"Paid Ads",'Cleaned Data'!K:K) -> 17630000
A14: =MIN('Cleaned Data'!L2:L31) -> 0 | D14: Social Media | E14: =SUMIF('Cleaned Data'!C:C, "Social Media", 'Cleaned Data'!K:K) -> 9100000
D15: Display | E15: =SUMIF('Cleaned Data'!C:C,"Display",'Cleaned Data'!K:K) -> 8240000
D16: Referral | E16: =SUMIF('Cleaned Data'!C:C, "Referral", 'Cleaned Data'!K:K) -> 8000000
D17: Organic | E17: =SUMIF('Cleaned Data'!C:C,"Organic",'Cleaned Data'!K:K) -> 4800000
D18: Video Ads | E18: =SUMIF('Cleaned Data'!C:C,"Video Ads",'Cleaned Data'!K:K) -> 4590000
D19: Influencer | E19: =SUMIF('Cleaned Data'!C:C,"Influencer",'Cleaned Data'!K:K) -> 3880000
D20: Affiliate | E20: =SUMIF('Cleaned Data'!C:C,"Affiliate",'Cleaned Data'!K:K) -> 1830000
D21: Audio Ads | E21: =SUMIF('Cleaned Data'!C:C,"Audio ads",'Cleaned Data'!K:K) -> 1400000
D22: Messaging | E22: =SUMIF('Cleaned Data'!C:C,"Messaging",'Cleaned Data'!K:K) -> 720000

Sheet Data Dictionary
A1: Data Dictionary
A2: Column Name | B2: Data Type | C2: Description | D2: Expected Values / Format | E2: Data Quality Notes
A3: Campaign_ID | B3: Text | C3: Unique campaign identifier | D3: C001, C002, C003 | E3: Duplicates removed using Campaign ID
A4: Campaign_Name | B4: Text | C4: Name of the campaign | D4: Text values | E4: Checked for consistency
A5: Channel | B5: Text | C5: Marketing channel used | D5: Email, Paid Ads, Social Media, etc. | E5: Standardized text values
A6: Start_Date | B6: Date | C6: Campaign start date | D6: YYYY-MM-DD | E6: Date format standardized
A7: End_Date | B7: Date | C7: Campaign end date | D7: YYYY-MM-DD | E7: Date format standardized; missing values reviewed
A8: Ad_Spend (NGN) | B8: Number | C8: Advertising cost in Naira | D8: Positive numeric values | E8: Commas removed and converted to numbers
A9: Impressions | B9: Number | C9: Number of ad views | D9: Whole numbers | E9: Converted to numeric format
A10: Clicks | B10: Number | C10: Number of ad clicks | D10: Whole numbers | E10: Converted to numeric format
A11: Leads | B11: Number | C11: Number of leads generated | D11: Whole numbers | E11: Converted to numeric format
A12: Conversions | B12: Number | C12: Number of successful conversions | D12: Whole numbers | E12: Converted to numeric format
A13: Revenue (NGN) | B13: Number | C13: Revenue generated in Naira | D13: Positive numeric values | E13: Dashes replaced with 0 where applicable
... A17: Account_Manager | B17: Text | C17: Campaign manager name | D17: Staff names | E17: Blank cells replaced with "Unknown - Pending Confirmation"

Sheet Pivot Table
A3: Campaign Name | B3: Average of ROI (%) | E3: Month | F3: Sum of Revenue (NGN) | H3: Sum of Revenue (NGN)
A4: Display Ads 0 Q3 | B4: 668 | E4: July | F4: 34440000 | H4: 68770000
A5: End0of0Quarter Blast | B5: 700 | E5: August | F5: 18040000
A6: Influencer Collab Aug | B6: 547 | E6: September | F6: 16290000
A7: Referral Programme | B7: 3100 | E7: Grand Total | F7: 68770000
A8: Twitter/X Campaign | B8: 805
A9: Grand Total | B9: 1164
E11: Channel | F11: Sum of Revenue (NGN) | G11: Sum of Ad_Spend (NGN) | H11: Sum of Conversions
C12: =GETPIVOTDATA("[Measures].[Sum of Revenue (NGN)]",$A$14) -> 68770000 | E12: Affiliate | F12: 1830000 | G12: 380000 | H12: 61
E13: Audio Ads | F13: 1400000 | G13: 680000 | H13: 35
A14: Sum of Revenue (NGN) | E14: Display | F14: 8240000 | G14: 1240000 | H14: 206
A15: 68770000 | C15: =GETPIVOTDATA("[Measures].[Sum of Revenue (NGN)]",$A$14) -> 68770000 | E15: Email | F15: 8580000 | G15: 1345000 | H15: 226
C16: =GETPIVOTDATA("[Measures].[Sum of Revenue (NGN)]",$A$14) -> 68770000 | E16: Influencer | F16: 3880000 | G16: 600000 | H16: 97
E17: Messaging | F17: 720000 | G17: 0 | H17: 18
A18: Sum of Ad_Spend (NGN) | E18: Organic | F18: 4800000 | G18: 0 | H18: 120
A19: 11495000 | C19: 11495000 | E19: Paid Ads | F19: 17630000 | G19: 4530000 | H19: 455
E20: Referral | F20: 8000000 | G20: 250000 | H20: 200
E21: Social Media | F21: 9100000 | G21: 1530000 | H21: 264
A22: Average of ROI (%) | E22: Video Ads | F22: 4590000 | G22: 940000 | H22: 153
A23: 400.1 | C23: 400.1 | E23: Grand Total | F23: 68770000 | G23: 11495000 | H23: 1835
A26: Sum of Leads | C26: Sum of Conversions
A27: 8003 | C27: 1835 | F27: =GETPIVOTDATA("[Measures].[Sum of Revenue (NGN)]",$A$14) -> 68770000
A29: 8003 | C29: 1835
E37: Month | F37: Sum of Revenue (NGN) | G37: Sum of Ad_Spend (NGN) | H37: Average of ROI (%) | I37: Sum of Conversions | J37: Sum of Leads
E38: July | F38: 34440000 | G38: 4565000 | H38: 513.90909 | I38: 915 | J38: 3875
E39: August | F39: 18040000 | G39: 3330000 | H39: 398.44444 | I39: 507 | J39: 2400
E40: September | F40: 16290000 | G40: 3600000 | H40: 276.4 | I40: 413 | J40: 1728
E41: Grand Total | F41: 68770000 | G41: 11495000 | H41: 400.1 | I41: 1835 | J41: 8003

Sheet Dashboard

Sheet Trends and Projections
U18: Z

Sheet Q4 Projections
A1: Month | B1: Revenue | C1: Growth Rate
A2: July | B2: 34440000
A3: August | B3: 18040000 | C3: -0.4762
A4: September | B4: 16290000 | C4: -0.097
A5: Average Growth | C5: =AVERAGE(C3:C4) -> -0.2866
A6: October | B6: 11621309
A7: November | B7: 8290533.1
A8: December | B8: 5914690.3

Sheet Competitor Comparison
A1: Metric | B1: Tech Savvy Solutions | C1: BrandPulse NG | D1: AdVance Digital
A2: Average Campaign ROI | B2: 4.001 | C2: 2.2 | D2: 1.85
A3: Average Cost per Lead | B3: 383167 | C3: ₦2,800 | D3: ₦3,400
A4: Top Channel | B4: Referral Programme | C4: Paid Ads | D4: Social Media
A5: Average Conversion Rate | B5: 61.17 | C5: 0.18 | D5: ₦21,000,000
A6: Total Q3 Revenue | B6: 68770000 | C6: ₦28,000,000 | D6: ₦21,000,000
